anime4k_python/__init__.py
anime4k_python/anime4k.py
anime4k_python/shaders/Anime4K_ModeA.glsl
anime4k_python-1.1.3.dist-info/LICENSE
anime4k_python-1.1.3.dist-info/METADATA
anime4k_python-1.1.3.dist-info/WHEEL
anime4k_python-1.1.3.dist-info/top_level.txt
anime4k_python-1.1.3.dist-info/RECORD
