Metadata-Version: 2.1
Name: anime4k_python
Version: 1.1.3
Summary: Python wrapper of Anime4K GLSL shaders achieved with FFmpeg and libplacebo
Author: K4YT3X
Author-email: i@k4yt3x.com
License: MIT
Keywords: anime4k,ffmpeg,upscaling
Classifier: Environment :: Console
Classifier: Programming Language :: Python
Classifier: Programming Language :: Python :: 3
Classifier: Operating System :: OS Independent
Requires-Python: >=3.7
License-File: LICENSE
Requires-Dist: ffmpeg-python >=0.2.0
Requires-Dist: pillow >=9.1.0
